smeasures/__init__.py
smeasures/cpumonitor.py
smeasures/measure.py
smeasures-0.1.5.dist-info/METADATA
smeasures-0.1.5.dist-info/WHEEL
smeasures-0.1.5.dist-info/top_level.txt
smeasures-0.1.5.dist-info/RECORD
