Metadata-Version: 2.1
Name: smeasures
Version: 0.1.5
Summary: Python package to easily capture respource utilization and time taken for given code block or method.
Home-page: https://github.com/csseeker/smeasures
Author: Shripad Kandharkar
Author-email: shripad.kandharkar@gmail.com
Classifier: Development Status :: 3 - Alpha
Classifier: Intended Audience :: Developers
Classifier: License :: OSI Approved :: MIT License
Classifier: Programming Language :: Python :: 3
Classifier: Programming Language :: Python :: 3.6
Classifier: Programming Language :: Python :: 3.7
Classifier: Programming Language :: Python :: 3.8
Classifier: Programming Language :: Python :: 3.9
Requires-Dist: psutil >=5.9.5
